tkxml/__init__.py
tkxml/constants.py
tkxml/decorators.py
tkxml/namespace.py
tkxml/settings.py
tkxml/tkxmlhandle.py
tkxml-1.0.0.dist-info/LICENSE
tkxml-1.0.0.dist-info/METADATA
tkxml-1.0.0.dist-info/WHEEL
tkxml-1.0.0.dist-info/top_level.txt
tkxml-1.0.0.dist-info/RECORD
