Metadata-Version: 2.1
Name: tkxml
Version: 1.0.0
Summary: Using XML to layout tkinter widgets.
Home-page: https://github.com/numlinka/pytkxml
Author: numlinka
Author-email: numlinka@163.com
License: LGPLv3
Keywords: tkinter,xml
Classifier: License :: OSI Approved :: GNU Lesser General Public License v3 (LGPLv3)
Classifier: Programming Language :: Python :: 3
License-File: LICENSE
